fast_bioservices/__init__.py
fast_bioservices/fast_http.py
fast_bioservices/settings.py
fast_bioservices/bigg/__init__.py
fast_bioservices/bigg/bigg.py
fast_bioservices/biodbnet/__init__.py
fast_bioservices/biodbnet/biodbnet.py
fast_bioservices/biodbnet/nodes.py
fast_bioservices/biothings/__init__.py
fast_bioservices/biothings/mygene.py
fast_bioservices/common/__init__.py
fast_bioservices/common/ensembl.py
fast_bioservices/ensembl/__init__.py
fast_bioservices/ensembl/cross_references.py
fast_bioservices/ensembl/lookup.py
fast_bioservices/kegg/__init__.py
fast_bioservices/ncbi/__init__.py
fast_bioservices/ncbi/datasets.py
fast_bioservices/pathway_commons/__init__.py
fast_bioservices/pipeline/__init__.py
fast_bioservices-0.3.9.dist-info/METADATA
fast_bioservices-0.3.9.dist-info/WHEEL
fast_bioservices-0.3.9.dist-info/RECORD
