Metadata-Version: 2.3
Name: fast-bioservices
Version: 0.3.9
Summary: Add your description here
Requires-Python: >=3.9
Requires-Dist: aiofiles>=24.1.0
Requires-Dist: appdirs>=1.4.4
Requires-Dist: hishel>=0.1.1
Requires-Dist: httpx>=0.27.2
Requires-Dist: loguru>=0.7.2
Requires-Dist: pandas>=1.5.3
